MANIFEST.in
setup.py
resweb/__init__.py
resweb/core.py
resweb/default_settings.py
resweb/views.py
resweb/static/idle.png
resweb/static/jquery-1.3.2.min.js
resweb/static/jquery.relatize_date.js
resweb/static/poll.png
resweb/static/ranger.js
resweb/static/reset.css
resweb/static/style.css
resweb/static/working.png
resweb/templates/base.html
resweb/templates/delayed.html
resweb/templates/delayed_timestamp.html
resweb/templates/failed.html
resweb/templates/macros.html
resweb/templates/overview.html
resweb/templates/queue.html
resweb/templates/queues.html
resweb/templates/stat.html
resweb/templates/stats.html
resweb/templates/worker.html
resweb/templates/workers.html
resweb/templates/working.html
resweb_dc.egg-info/PKG-INFO
resweb_dc.egg-info/SOURCES.txt
resweb_dc.egg-info/dependency_links.txt
resweb_dc.egg-info/entry_points.txt
resweb_dc.egg-info/requires.txt
resweb_dc.egg-info/top_level.txt