Metadata-Version: 1.1
Name: resweb-dc
Version: 0.1.9
Summary: Pyres web interface
Home-page: https://github.com/dawncold/resweb
Author: dc
Author-email: loooseleaves@gmail.com
License: MIT
Platform: UNKNOWN
Classifier: Development Status :: 4 - Beta
Classifier: Environment :: Console
Classifier: Intended Audience :: Developers
Classifier: License :: OSI Approved :: MIT License
Classifier: Operating System :: OS Independent
Classifier: Programming Language :: Python
